control_server_pb2.py
control_server_pb2_grpc.py
pyscalebox.py
pyscalebox-0.0.3.dist-info/METADATA
pyscalebox-0.0.3.dist-info/WHEEL
pyscalebox-0.0.3.dist-info/top_level.txt
pyscalebox-0.0.3.dist-info/RECORD
