Metadata-Version: 2.1
Name: pyscalebox
Version: 0.0.3
Summary: level 2 pipeline api:send_message(body)
Home-page: UNKNOWN
Author: zhangxiaoli
Author-email: zhangxiaoli@cnic.cn
License: apache 3.0
Platform: UNKNOWN
Requires: os
Requires: grpc
